configmate_plugins/pydantic_validator/__init__.py
configmate_plugins/pydantic_validator/pydantic_validator.py
configmate_pydantic_validator-0.1.0.dist-info/METADATA
configmate_pydantic_validator-0.1.0.dist-info/WHEEL
configmate_pydantic_validator-0.1.0.dist-info/RECORD
