Metadata-Version: 2.1
Name: configmate-pydantic-validator
Version: 0.1.0
Summary: Extends configmate with pydantic validation logic.
Author: Arthur Böök
Requires-Python: >=3.8,<4.0
Classifier: Programming Language :: Python :: 3
Classifier: Programming Language :: Python :: 3.8
Classifier: Programming Language :: Python :: 3.9
Classifier: Programming Language :: Python :: 3.10
Classifier: Programming Language :: Python :: 3.11
Classifier: Programming Language :: Python :: 3.12
Requires-Dist: configmate (>=0.1.8,<0.2.0)
Requires-Dist: pydantic (>=1.0,<3.0)
